colrs/__init__.py
colrs/actions.py
colrs/animations.py
colrs/async_tools.py
colrs/components.py
colrs/core.py
colrs/effects.py
colrs/layout.py
colrs/live.py
colrs/logger.py
colrs/magic.py
colrs/menus.py
colrs/panel.py
colrs/progress.py
colrs/shapes.py
colrs/style_1.py
colrs/style_10.py
colrs/style_2.py
colrs/style_3.py
colrs/style_4.py
colrs/style_5.py
colrs/style_6.py
colrs/style_7.py
colrs/style_8.py
colrs/style_9.py
colrs/tables.py
colrs/theme.py
colrs-0.4.dist-info/licenses/LICENSE
colrs-0.4.dist-info/METADATA
colrs-0.4.dist-info/WHEEL
colrs-0.4.dist-info/top_level.txt
colrs-0.4.dist-info/RECORD
